cd3_connector/__init__.py
cd3_connector/__init__310.pyc
cd3_connector/__init__311.pyc
cd3_connector/__init__312.pyc
cd3_connector/__init__313.pyc
cd3_connector/__init__38.pyc
cd3_connector/__init__39.pyc
cd3_connector/cd3_connector310.pyc
cd3_connector/cd3_connector311.pyc
cd3_connector/cd3_connector312.pyc
cd3_connector/cd3_connector313.pyc
cd3_connector/cd3_connector38.pyc
cd3_connector/cd3_connector39.pyc
cd3_connector-0.3.1.dist-info/METADATA
cd3_connector-0.3.1.dist-info/WHEEL
cd3_connector-0.3.1.dist-info/top_level.txt
cd3_connector-0.3.1.dist-info/RECORD
