Metadata-Version: 2.4
Name: cd3_connector
Version: 0.3.1
Summary: Biblioteca para facilitar conexão e comunicação com o Market Data Cedro
Author: Cedro Technologies
Author-email: cd3connector@cedrotech.com
Classifier: Programming Language :: Python :: 3
Classifier: License :: OSI Approved :: MIT License
Classifier: Operating System :: OS Independent
Requires-Python: >=3.8
Dynamic: author
Dynamic: author-email
Dynamic: classifier
Dynamic: requires-python
Dynamic: summary
